merge_sqlite/__init__.py
merge_sqlite/__main__.py
merge_sqlite/main.py
merge_sqlite-0.16.dist-info/DESCRIPTION.rst
merge_sqlite-0.16.dist-info/METADATA
merge_sqlite-0.16.dist-info/RECORD
merge_sqlite-0.16.dist-info/WHEEL
merge_sqlite-0.16.dist-info/metadata.json
merge_sqlite-0.16.dist-info/top_level.txt
