Metadata-Version: 2.0
Name: merge-sqlite
Version: 0.16
Summary: merge arbitrary number of sqlite files
Home-page: https://github.com/jeremiahsavage/merge_sqlite
Author: Jeremiah H. Savage
Author-email: jeremiahsavage@gmail.com
License: Apache 2.0
Platform: UNKNOWN
Classifier: Development Status :: 3 - Alpha
Classifier: Intended Audience :: Developers
Classifier: License :: OSI Approved :: Apache Software License
Classifier: Programming Language :: Python
Classifier: Programming Language :: Python :: 2
Classifier: Programming Language :: Python :: 3
Requires-Dist: cdis-pipe-utils
Requires-Dist: pandas
Requires-Dist: sqlalchemy
